examples/policy_improvement_demo.py
examples/visualization_demo.py
mctx/__init__.py
mctx/py.typed
mctx/_src/__init__.py
mctx/_src/action_selection.py
mctx/_src/base.py
mctx/_src/policies.py
mctx/_src/qtransforms.py
mctx/_src/search.py
mctx/_src/seq_halving.py
mctx/_src/tree.py
mctx/_src/tests/mctx_test.py
mctx/_src/tests/policies_test.py
mctx/_src/tests/qtransforms_test.py
mctx/_src/tests/seq_halving_test.py
mctx/_src/tests/tree_test.py
mctx-0.0.6.dist-info/licenses/LICENSE
mctx-0.0.6.dist-info/METADATA
mctx-0.0.6.dist-info/WHEEL
mctx-0.0.6.dist-info/top_level.txt
mctx-0.0.6.dist-info/RECORD
