Metadata-Version: 2.4
Name: mctx
Version: 0.0.6
Summary: Monte Carlo tree search in JAX.
Home-page: https://github.com/google-deepmind/mctx
Author: DeepMind
Author-email: mctx-dev@google.com
License: Apache 2.0
Keywords: jax planning reinforcement-learning python machine learning
Classifier: Development Status :: 4 - Beta
Classifier: Intended Audience :: Science/Research
Classifier: License :: OSI Approved :: Apache Software License
Classifier: Programming Language :: Python
Classifier: Programming Language :: Python :: 3
Classifier: Topic :: Scientific/Engineering :: Artificial Intelligence
Classifier: Topic :: Software Development :: Libraries :: Python Modules
Requires-Python: >=3.11
License-File: LICENSE
Requires-Dist: chex>=0.1.91
Requires-Dist: jax>=0.7.0
Requires-Dist: jaxlib>=0.7.0
Dynamic: author
Dynamic: author-email
Dynamic: classifier
Dynamic: description
Dynamic: description-content-type
Dynamic: home-page
Dynamic: keywords
Dynamic: license
Dynamic: license-file
Dynamic: requires-dist
Dynamic: requires-python
Dynamic: summary
